{"chunk_definitions":[{"row":79,"row_count":1,"visible":true,"expansion_state":0,"options":{"engine":"r","label":"setup","include":false},"document_id":"427530A9","chunk_id":"csetup_chunk","chunk_label":"setup"},{"row":101,"row_count":1,"visible":true,"expansion_state":0,"options":{"engine":"r","label":"unnamed-chunk-6"},"document_id":"427530A9","chunk_id":"cbwmqv5rht7o4","chunk_label":"unnamed-chunk-1"}],"doc_write_time":1641511249,"working_dir":null,"default_chunk_options":{"echo":true,"warning":false}}